{
  "klowns": [
    {
      "id": 1,
      "name": "Joker",
      "health": 100,
      "image": "https://img.cinemablend.com/filter:scale/quill/e/4/7/0/2/8/e470289e30be3f30a4003e98c0e1103ebdc32f7a.jpg?mw=600"
    },
    {
      "id": 2,
      "name": "PennyWise",
      "health": 100,
      "image": "https://i.ytimg.com/vi/aW19ur93Y6o/maxresdefault.jpg"
    },
    {
      "name": "Dan",
      "image": "http://drklown.org/wp-content/uploads/2016/02/drbig.jpg",
      "health": 100,
      "id": 3
    },
    {
      "name": "Dan",
      "image": "http://drklown.org/wp-content/uploads/2016/02/drbig.jpg",
      "health": 100,
      "id": 4
    }
  ],
  "humans": [
    {
      "id": 1,
      "name": "Debbie Stone",
      "health": 100,
      "image": "http://geekchocolate.co.uk/wp-content/uploads/2015/02/2014pt3_BookFest_klowns-7.jpg"
    },
    {
      "id": 2,
      "name": "Curtis Mooney",
      "health": 100,
      "image": "https://vignette.wikia.nocookie.net/to-hollywood-and-beyond/images/7/70/Curtis_Mooney_klowns.jpg/revision/latest?cb=20170106221045"
    }
  ]
}